humanmint/__init__.py
humanmint/cli.py
humanmint/column_guess.py
humanmint/compare.py
humanmint/export.py
humanmint/gliner.py
humanmint/mint.py
humanmint/pandas.py
humanmint/pandas_ext.py
humanmint/processors.py
humanmint/py.typed
humanmint/semantics.py
humanmint/text_clean.py
humanmint/types.py
humanmint/addresses/__init__.py
humanmint/addresses/normalize.py
humanmint/constants/__init__.py
humanmint/constants/garbled.py
humanmint/constants/names.py
humanmint/constants/titles.py
humanmint/data/bls_titles.json.gz
humanmint/data/department_abbreviations.json.gz
humanmint/data/department_categories.json.gz
humanmint/data/department_mappings_list.json.gz
humanmint/data/free_email_providers.json.gz
humanmint/data/generic_inboxes.json.gz
humanmint/data/job_titles.json.gz
humanmint/data/name_corporate_terms.json.gz
humanmint/data/name_credential_suffixes.json.gz
humanmint/data/name_generational_suffixes.json.gz
humanmint/data/name_non_person_phrases.json.gz
humanmint/data/name_placeholder_names.json.gz
humanmint/data/name_roman_numerals.json.gz
humanmint/data/name_title_prefixes.json.gz
humanmint/data/names.json.gz
humanmint/data/semantic_tokens.json.gz
humanmint/data/seniority_keywords.json.gz
humanmint/data/title_abbreviations.json.gz
humanmint/data/title_heuristics.json.gz
humanmint/data/title_preserve_abbreviations.json.gz
humanmint/data/title_stopwords.json.gz
humanmint/data/utils.py
humanmint/departments/__init__.py
humanmint/departments/categories.py
humanmint/departments/data_loader.py
humanmint/departments/matching.py
humanmint/departments/normalize.py
humanmint/emails/__init__.py
humanmint/emails/_pattern_definitions.py
humanmint/emails/classifier.py
humanmint/emails/normalize.py
humanmint/emails/patterns.py
humanmint/names/__init__.py
humanmint/names/enrichment.py
humanmint/names/garbled.py
humanmint/names/matching.py
humanmint/names/normalize.py
humanmint/organizations/__init__.py
humanmint/organizations/normalize.py
humanmint/phones/__init__.py
humanmint-2.0.1.dist-info/licenses/LICENSE
humanmint-2.0.1.dist-info/METADATA
humanmint-2.0.1.dist-info/WHEEL
humanmint-2.0.1.dist-info/entry_points.txt
humanmint-2.0.1.dist-info/top_level.txt
humanmint-2.0.1.dist-info/RECORD
