Metadata-Version: 2.4
Name: humanmint
Version: 2.0.1
Summary: Clean, functional data processing for human-centric applications. Normalize and standardize names, emails, phones, departments, and job titles with a single unified API.
Author: Ricardo Nunes
License-Expression: MIT
Project-URL: Homepage, https://github.com/RicardoNunes2000/HumanMint
Project-URL: Documentation, https://github.com/RicardoNunes2000/HumanMint#documentation
Project-URL: API Reference, https://github.com/RicardoNunes2000/HumanMint/blob/main/README.md#api-reference
Project-URL: Use Cases, https://github.com/RicardoNunes2000/HumanMint/tree/main/docs/use_cases
Project-URL: Fields Guide, https://github.com/RicardoNunes2000/HumanMint/blob/main/docs/FIELDS.md
Project-URL: Bug Tracker, https://github.com/RicardoNunes2000/HumanMint/issues
Project-URL: Source Code, https://github.com/RicardoNunes2000/HumanMint
Project-URL: Changelog, https://github.com/RicardoNunes2000/HumanMint/blob/main/CHANGELOG.md
Keywords: data-processing,normalization,names,emails,phones,departments,titles,civic-data
Classifier: Development Status :: 3 - Alpha
Classifier: Intended Audience :: Developers
Classifier: Programming Language :: Python :: 3
Classifier: Programming Language :: Python :: 3.8
Classifier: Programming Language :: Python :: 3.9
Classifier: Programming Language :: Python :: 3.10
Classifier: Programming Language :: Python :: 3.11
Classifier: Programming Language :: Python :: 3.12
Classifier: Operating System :: OS Independent
Classifier: Topic :: Office/Business
Classifier: Topic :: Text Processing
Requires-Python: >=3.8
License-File: LICENSE
Requires-Dist: email-validator>=2.0.0
Requires-Dist: phonenumbers>=8.13.0
Requires-Dist: nameparser>=1.1.0
Requires-Dist: nicknames>=0.0.2
Requires-Dist: rapidfuzz>=3.6
Requires-Dist: orjson>=3.10
Requires-Dist: ftfy>=6.1.0
Requires-Dist: importlib_resources>=5.0; python_version < "3.9"
Provides-Extra: dev
Requires-Dist: pytest>=7.0; extra == "dev"
Requires-Dist: black>=23.0; extra == "dev"
Requires-Dist: flake8>=6.0; extra == "dev"
Requires-Dist: mypy>=1.0; extra == "dev"
Requires-Dist: faker>=20.0; extra == "dev"
Provides-Extra: address
Requires-Dist: usaddress>=0.6.0; extra == "address"
Provides-Extra: pandas
Requires-Dist: pandas>=1.5; extra == "pandas"
Provides-Extra: ml
Requires-Dist: gliner2>=0.2.0; extra == "ml"
Dynamic: license-file
